minsert/__init__.py
minsert/minsert.py
minsert-0.1.0.dist-info/LICENSE
minsert-0.1.0.dist-info/WHEEL
minsert-0.1.0.dist-info/METADATA
minsert-0.1.0.dist-info/RECORD
