Metadata-Version: 2.1
Name: minsert
Version: 0.1.0
Summary: Insert dynamic content in markdown, without using a separate template file.
Home-page: https://github.com/aahnik/minsert
License: MIT
Keywords: python,cli,markdown,file
Author: aahnik
Author-email: daw@aahnik.dev
Requires-Python: >=3.8,<4.0
Classifier: Development Status :: 4 - Beta
Classifier: Intended Audience :: Education
Classifier: Intended Audience :: Information Technology
Classifier: License :: OSI Approved :: MIT License
Classifier: Natural Language :: English
Classifier: Operating System :: OS Independent
Classifier: Programming Language :: Python
Classifier: Programming Language :: Python :: 3
Classifier: Programming Language :: Python :: 3.8
Classifier: Programming Language :: Python :: 3.9
Project-URL: Repository, https://github.com/aahnik/minsert
